{"frameRate":30,"name":"go_friend_text","version":"5.5","compatibleVersion":"5.5","armature":[{"type":"Armature","frameRate":30,"name":"animate","aabb":{"x":17.7,"y":401.4,"width":391.02,"height":99},"bone":[{"name":"root","transform":{"skX":0.0221,"skY":0.0221}},{"name":"去開場房","parent":"root","transform":{"x":130.6785,"y":463.4497}},{"name":"Board_And_Card_Games","parent":"root","transform":{"x":129.6636,"y":424.8001}},{"name":"go","parent":"root","transform":{"x":263.3735,"y":450.4986}},{"name":"箭頭001","parent":"root","transform":{"x":359.3655,"y":429.8116}},{"name":"箭頭002","parent":"root","transform":{"x":386.19,"y":430.127}},{"name":"bone","parent":"root"}],"slot":[{"name":"去開場房","parent":"去開場房"},{"name":"Board_And_Card_Games","parent":"Board_And_Card_Games"},{"name":"go","parent":"go"},{"name":"箭頭02","parent":"箭頭001"},{"name":"箭頭021","parent":"箭頭002"}],"skin":[{"slot":[{"name":"go","display":[{"name":"parts/go/go","transform":{"x":0.1,"y":0.3}}]},{"name":"去開場房","display":[{"name":"parts/去開場房/去開場房","transform":{"x":0.2,"y":0.25}}]},{"name":"Board_And_Card_Games","display":[{"name":"parts/Board And Card Games/Board And Card Games","transform":{"x":0.25,"y":0.35}}]},{"name":"箭頭02","display":[{"name":"parts/箭頭02/箭頭02","transform":{"x":0.2,"y":0.25}}]},{"name":"箭頭021","display":[{"name":"parts/箭頭02/箭頭02","transform":{"x":0.2,"y":0.25}}]}]}],"animation":[{"duration":60,"fadeInTime":1,"name":"animate","bone":[{"name":"去開場房","translateFrame":[{"duration":10},{"duration":20,"curve":[0,0,0.5,1],"x":-241.74},{"duration":30,"x":-1.16}]},{"name":"Board_And_Card_Games","translateFrame":[{"duration":20,"curve":[0,0,0.1055363321799308,1.0244565217391304],"x":-240.46},{"duration":40,"x":0.26}]},{"name":"go","translateFrame":[{"duration":24},{"duration":12,"curve":[0,0,0.185121107266436,1],"x":-64.1},{"duration":24,"x":-2.46}]},{"name":"箭頭001","translateFrame":[{"duration":32,"tweenEasing":0,"x":-15.61},{"duration":6,"tweenEasing":0,"x":-15.61},{"duration":22,"x":0.82}]},{"name":"箭頭002","translateFrame":[{"duration":36,"tweenEasing":0,"x":-26.24},{"duration":6,"tweenEasing":0,"x":-25.42},{"duration":18,"x":2.52}]}],"slot":[{"name":"箭頭02","colorFrame":[{"duration":32,"value":{"aM":0}},{"duration":6,"tweenEasing":0,"value":{"aM":0}},{"duration":22}]},{"name":"go","colorFrame":[{"duration":24,"value":{"aM":0}},{"duration":12,"tweenEasing":0,"value":{"aM":0}},{"duration":24}]},{"name":"Board_And_Card_Games","colorFrame":[{"duration":20,"tweenEasing":0,"value":{"aM":0}},{"duration":40}]},{"name":"去開場房","colorFrame":[{"duration":10,"tweenEasing":0,"value":{"aM":0}},{"duration":20,"curve":[0,0,0.5,1],"value":{"aM":0}},{"duration":30}]},{"name":"箭頭021","colorFrame":[{"duration":36,"value":{"aM":0}},{"duration":6,"tweenEasing":0,"value":{"aM":0}},{"duration":18}]}]}],"defaultActions":[{"gotoAndPlay":"animate"}]}]}